Flask_Authbone-0.3.dist-info/DESCRIPTION.rst
Flask_Authbone-0.3.dist-info/METADATA
Flask_Authbone-0.3.dist-info/RECORD
Flask_Authbone-0.3.dist-info/WHEEL
Flask_Authbone-0.3.dist-info/metadata.json
Flask_Authbone-0.3.dist-info/top_level.txt
authbone/__init__.py
authbone/auth_data_getters.py
authbone/authentication.py
authbone/authorization.py
